mr_s3/__init__.py
mr_s3/pull.py
mr_s3/push.py
mr_s3/router.py
mr.s3-1.0.0b3.dist-info/LICENSE
mr.s3-1.0.0b3.dist-info/METADATA
mr.s3-1.0.0b3.dist-info/WHEEL
mr.s3-1.0.0b3.dist-info/entry_points.txt
mr.s3-1.0.0b3.dist-info/top_level.txt
mr.s3-1.0.0b3.dist-info/RECORD
