Metadata-Version: 2.1
Name: mr.s3
Version: 1.0.0b3
Summary: Syncing scripts Plone data between local and AWS S3
Home-page: https://github.com/peacock0803sz/mr.s3
Author: Peacock
Author-email: contact@peacock0803sz.com
License: UNKNOWN
Keywords: Plone Python AWS
Platform: UNKNOWN
Classifier: Programming Language :: Python :: 3
Classifier: Development Status :: 4 - Beta
Classifier: Environment :: Console
Classifier: Framework :: Plone
Requires-Dist: click
Requires-Dist: boto3
Requires-Dist: boto3-stubs[s3]
Provides-Extra: tests
Requires-Dist: pytest ; extra == 'tests'
Requires-Dist: moto ; extra == 'tests'
